corpus_replicator/__init__.py
corpus_replicator/__main__.py
corpus_replicator/common.py
corpus_replicator/core.py
corpus_replicator/generate_corpus.py
corpus_replicator/generate_template.py
corpus_replicator/test_common.py
corpus_replicator/test_generate_corpus.py
corpus_replicator/test_generate_template.py
corpus_replicator/test_replicator.py
corpus_replicator/recipes/animation_apng_png_ffmpeg.yml
corpus_replicator/recipes/animation_gif_gif_ffmpeg.yml
corpus_replicator/recipes/animation_webp_webp_libwebp.yml
corpus_replicator/recipes/audio_aac_mp4_ffmpeg.yml
corpus_replicator/recipes/audio_flac_flac_libflac.yml
corpus_replicator/recipes/audio_mp3_mp3_libmp3lame.yml
corpus_replicator/recipes/audio_mp3_mp3_shine.yml
corpus_replicator/recipes/audio_opus_opus_libopus.yml
corpus_replicator/recipes/audio_pcm_wav_ffmpeg.yml
corpus_replicator/recipes/audio_vorbis_ogg_libvorbis.yml
corpus_replicator/recipes/image_avif_avif_imagemagick.yml
corpus_replicator/recipes/image_bmp_bmp_ffmpeg.yml
corpus_replicator/recipes/image_gif_gif_ffmpeg.yml
corpus_replicator/recipes/image_heic_heic_imagemagick.yml
corpus_replicator/recipes/image_ico_ico_ffmpeg.yml
corpus_replicator/recipes/image_jpg_jpg_ffmpeg.yml
corpus_replicator/recipes/image_png_png_ffmpeg.yml
corpus_replicator/recipes/image_webp_webp_libwebp.yml
corpus_replicator/recipes/schema.json
corpus_replicator/recipes/video_av1_webm_libaom.yml
corpus_replicator/recipes/video_h264_264_libx264.yml
corpus_replicator/recipes/video_h264_mp4_libx264.yml
corpus_replicator/recipes/video_h265_mp4_libx265.yml
corpus_replicator/recipes/video_theora_ogg_libtheora.yml
corpus_replicator/recipes/video_vp8_webm_libvpx.yml
corpus_replicator/recipes/video_vp9_webm_libvpx.yml
corpus_replicator/recipes/video_xvid_mp4_libxvid.yml
corpus_replicator/tools/__init__.py
corpus_replicator/tools/ffmpeg.py
corpus_replicator/tools/imagemagick.py
corpus_replicator/tools/test_ffmpeg.py
corpus_replicator/tools/test_imagemagick.py
corpus_replicator-1.1.2.dist-info/LICENSE.md
corpus_replicator-1.1.2.dist-info/METADATA
corpus_replicator-1.1.2.dist-info/WHEEL
corpus_replicator-1.1.2.dist-info/entry_points.txt
corpus_replicator-1.1.2.dist-info/top_level.txt
corpus_replicator-1.1.2.dist-info/RECORD
