Metadata-Version: 2.1
Name: corpus-replicator
Version: 1.1.2
Home-page: https://github.com/MozillaSecurity/corpus-replicator
Author: Tyson Smith
Author-email: twsmith@mozilla.com
Maintainer: Mozilla Fuzzing Team
Maintainer-email: fuzzing@mozilla.com
License: MPL 2.0
Keywords: automation corpus fuzz fuzzing security test testing
Classifier: Intended Audience :: Developers
Classifier: License :: OSI Approved :: Mozilla Public License 2.0 (MPL 2.0)
Classifier: Programming Language :: Python :: 3
Classifier: Topic :: Software Development :: Testing
Requires-Python: >=3.8
License-File: LICENSE.md
Requires-Dist: PyYAML
Provides-Extra: dev
Requires-Dist: pre-commit ; extra == 'dev'
Requires-Dist: tox ; extra == 'dev'
